gotree/__init__.py
gotree/gotree.py
gotree-1.0.3.dist-info/LICENSE
gotree-1.0.3.dist-info/METADATA
gotree-1.0.3.dist-info/WHEEL
gotree-1.0.3.dist-info/top_level.txt
gotree-1.0.3.dist-info/RECORD
