Metadata-Version: 2.1
Name: gotree
Version: 1.0.3
Summary: A new solution to tree
Home-page: https://www.baidu.com
Author: Newman Lv
Author-email: 453276749@qq.com
License: UNKNOWN
Platform: UNKNOWN
Classifier: Programming Language :: Python :: 3
Classifier: License :: OSI Approved :: MIT License
Classifier: Operating System :: OS Independent
License-File: LICENSE
